spgateway/__init__.py
spgateway/apps.py
spgateway/forms.py
spgateway/helpers.py
spgateway/middleware.py
spgateway/models.py
spgateway/urls.py
spgateway/views.py
spgateway/migrations/0001_initial.py
spgateway/migrations/0002_generate_slug_for_none.py
spgateway/migrations/0003_auto_20180811_1809.py
spgateway/migrations/0004_spgatewaycustomerresponseinfo_order.py
spgateway/migrations/__init__.py
spgateway/templates/spgateway/response.html
django_spgateway-0.7.6.dist-info/AUTHORS.rst
django_spgateway-0.7.6.dist-info/LICENSE
django_spgateway-0.7.6.dist-info/METADATA
django_spgateway-0.7.6.dist-info/WHEEL
django_spgateway-0.7.6.dist-info/top_level.txt
django_spgateway-0.7.6.dist-info/RECORD
