Metadata-Version: 2.1
Name: django-spgateway
Version: 0.7.6
Summary: Django support for Spgateway
Home-page: https://github.com/cjltsod/django-spgateway
Author: CJLTSOD <github.tsod@tsod.idv.tw>
Author-email: github.tsod@tsod.idv.tw
License: MIT
Keywords: django,spgateway
Platform: UNKNOWN
Classifier: Development Status :: 2 - Pre-Alpha
Classifier: Programming Language :: Python
Classifier: Programming Language :: Python :: 3.7
Classifier: Topic :: Software Development :: Libraries :: Python Modules
Classifier: Framework :: Django
Classifier: Framework :: Django :: 2.1
Classifier: License :: OSI Approved :: MIT License
Classifier: Environment :: Web Environment
Requires-Dist: django (>=1.10)
Requires-Dist: pycrypto (>=2.6.1)
